databricks/__init__.py
databricks/vector_search/__init__.py
databricks/vector_search/client.py
databricks/vector_search/utils.py
databricks/vector_search/vs_utils.py
databricks_vectorsearch_preview-0.21.dist-info/LICENSE.md
databricks_vectorsearch_preview-0.21.dist-info/METADATA
databricks_vectorsearch_preview-0.21.dist-info/WHEEL
databricks_vectorsearch_preview-0.21.dist-info/top_level.txt
databricks_vectorsearch_preview-0.21.dist-info/RECORD
