Metadata-Version: 2.1
Name: databricks-vectorsearch-preview
Version: 0.21
Summary: Databricks Vector Search Client
Home-page: UNKNOWN
Author: Databricks
Author-email: feedback@databricks.com
License: UNKNOWN
Platform: UNKNOWN
Requires-Python: >=3.7
Requires-Dist: mlflow-skinny (<3,>=2.4.0)
Requires-Dist: protobuf (<5,>=3.12.0)
Requires-Dist: requests (>=2)
